iscc_sci/__init__.py
iscc_sci/cli.py
iscc_sci/code_semantic_image.py
iscc_sci/options.py
iscc_sci/utils.py
iscc_sci-0.2.0.dist-info/entry_points.txt
iscc_sci-0.2.0.dist-info/LICENSE
iscc_sci-0.2.0.dist-info/METADATA
iscc_sci-0.2.0.dist-info/WHEEL
iscc_sci-0.2.0.dist-info/RECORD
