Metadata-Version: 2.3
Name: iscc-sci
Version: 0.2.0
Summary: ISCC - Semantic Code Image
License: Apache-2.0
Keywords: iscc,semantic,media,hash,similarity
Author: Titusz
Author-email: tp@py7.de
Requires-Python: >=3.9,<4.0
Classifier: Development Status :: 4 - Beta
Classifier: Intended Audience :: Developers
Classifier: Intended Audience :: Science/Research
Classifier: License :: OSI Approved :: Apache Software License
Classifier: License :: OSI Approved :: BSD License
Classifier: Natural Language :: English
Classifier: Operating System :: OS Independent
Classifier: Programming Language :: Cython
Classifier: Programming Language :: Python :: 3
Classifier: Programming Language :: Python :: 3.9
Classifier: Programming Language :: Python :: 3.10
Classifier: Programming Language :: Python :: 3.11
Classifier: Programming Language :: Python :: 3.12
Classifier: Programming Language :: Python :: 3.13
Classifier: Topic :: Multimedia
Classifier: Topic :: Multimedia :: Graphics
Classifier: Topic :: Scientific/Engineering :: Image Recognition
Classifier: Topic :: Scientific/Engineering :: Information Analysis
Classifier: Topic :: Software Development :: Libraries :: Python Modules
Provides-Extra: gpu
Requires-Dist: blake3
Requires-Dist: loguru
Requires-Dist: onnxruntime
Requires-Dist: onnxruntime-gpu ; extra == "gpu"
Requires-Dist: pillow
Requires-Dist: platformdirs
Requires-Dist: pydantic-settings
Project-URL: Homepage, https://iscc.codes
Project-URL: Repository, https://github.com/iscc/iscc-sci
